{
  "$schema": "https://mintlify.com/schema.json",
  "name": "Goodfire SDK",
  "logo": {
    "dark": "/logo/goodfire-white.svg",
    "light": "/logo/goodfire-logo.svg"
  },
  "favicon": "/goodfire-mark.svg",
  "colors": {
    "primary": "#ed5700",
    "light": "#f7b100",
    "dark": "#d62c0b",
    "anchors": {
      "from": "#0D9373",
      "to": "#07C983"
    }
  },
  "topbarLinks": [
    {
      "name": "Support",
      "url": "mailto:support@goodfire.ai"
    }
  ],
  "topbarCtaButton": {
    "name": "Platform",
    "url": "https://platform.goodfire.ai/"
  },
  "tabs": [
    {
      "name": "SDK Reference",
      "url": "sdk-reference"
    }
  ],
  "navigation": [
    {
      "group": "Get Started",
      "pages": ["introduction", "quickstart"]
    },
    {
      "group": "Classes",
      "pages": [
        "sdk-reference/example",
        "sdk-reference/chat",
        "sdk-reference/variants",
        "sdk-reference/features",
        "sdk-reference/conditionals",
        "sdk-reference/autosteer"
      ]
    },
    {
      "group": "Notebooks",
      "pages": [
        "notebooks/decision-trees",
        "notebooks/jailbreak",
        "notebooks/ondemandrag",
        "notebooks/dynamicprompts",
        "notebooks/removing-knowledge",
        "notebooks/sortingfeatures"
      ]
    }
  ],
  "footerSocials": {
    "x": "https://x.com/GoodfireAI",
    "linkedin": "https://www.linkedin.com/company/goodfire-ai/"
  }
}
